AC/726020_Cecilia_Bouchardet_Guia_09/Exemplo_0904.v
// ---------------------------
// -- test clock generator (2)
// -- Cecilia Capurucho Bouchardet
// ---------------------------
module clock ( output clk );
    reg clk;
    initial begin
        clk = 1'b0;
    end
    always begin
        #6 clk = ~clk;
        
    end
endmodule
module pulse ( signal, clock );
    input clock;
    output signal;
    reg signal;
    always @ ( clock ) begin
        signal = 1'b1;
        #3 signal = 1'b0;
        #3 signal = 1'b1;
        #3 signal = 1'b0;
    end
endmodule // pulse
module trigger ( signal, on, clock );
    input on, clock;
    output signal;
    reg signal;
    always @ ( posedge clock & on ) begin
        #60 signal = 1'b1;
        #60 signal = 1'b0;
    end
endmodule // trigger
module Exemplo_0904;
    wire clock;
    clock clk ( clock );
    reg p;
    wire p1,t1;
    pulse pulse1 ( p1, clock );
    trigger trigger1 ( t1, p, clock );
    initial begin
        p = 1'b0;
    end
    initial begin
        $dumpfile ( "Exemplo0904.vcd" );
        $dumpvars ( 1, clock, p1, p, t1 );
        #060 p = 1'b1;
        #120 p = 1'b0;
        #180 p = 1'b1;
        #240 p = 1'b0;
        #300 p = 1'b1;
        #360 p = 1'b0;
        #376 $finish;
    end
endmodule // Exemplo_0902

/*
---------------------------------------------------
PREVISÃO DE TESTES
----------------------------------------------------
METODO CLOCK
Primeiramente vai valer 0 por 12 segundos
Depois valendo 0
----------------------------------------------------
METODO PULSE
Primeiramnete o sinal vale 1
Depois de 3 segundos vale 0
Depois de 3 segundos vale 1
Depois de 3 segundos vale 0
-----------------------------------------------------
EXEMPLO_0904
p começa valendo 0
cria o arquivo " Exemplo0902.vcd"
Depois de 60 segundos vale 1
Depois de 120 segundos vale 0
Depois de 180 segundos vale 1
Depois de 240 segundos vale 0
Depois de 300 segundos vale 1
Depois de 360 segundos vale 0
Depois de 376 segundos termina
------------------------------------------------------
*/

AC/726020_Cecilia_Bouchardet_Guia_09/Exemplo0904.vcd
$date
	Fri Oct  1 15:57:44 2021
$end
$version
	Icarus Verilog
$end
$timescale
	1s
$end
$scope module Exemplo_0904 $end
$var wire 1 ! clock $end
$upscope $end
$scope module Exemplo_0904 $end
$var wire 1 " p1 $end
$upscope $end
$scope module Exemplo_0904 $end
$var reg 1 # p $end
$upscope $end
$scope module Exemplo_0904 $end
$var wire 1 $ t1 $end
$upscope $end
$enddefinitions $end
#0
$dumpvars
x$
0#
1"
0!
$end
#3
0"
#6
1"
1!
#9
0"
#12
1"
0!
#15
0"
#18
1"
1!
#21
0"
#24
1"
0!
#27
0"
#30
1"
1!
#33
0"
#36
1"
0!
#39
0"
#42
1"
1!
#45
0"
#48
1"
0!
#51
0"
#54
1"
1!
#57
0"
#60
1"
0!
1#
#63
0"
#66
1"
1!
#69
0"
#72
1"
0!
#75
0"
#78
1"
1!
#81
0"
#84
1"
0!
#87
0"
#90
1"
1!
#93
0"
#96
1"
0!
#99
0"
#102
1"
1!
#105
0"
#108
1"
0!
#111
0"
#114
1"
1!
#117
0"
#120
1"
0!
#123
0"
#126
1"
1!
1$
#129
0"
#132
1"
0!
#135
0"
#138
1"
1!
#141
0"
#144
1"
0!
#147
0"
#150
1"
1!
#153
0"
#156
1"
0!
#159
0"
#162
1"
1!
#165
0"
#168
1"
0!
#171
0"
#174
1"
1!
#177
0"
#180
1"
0!
0#
#183
0"
#186
1"
1!
0$
#189
0"
#192
1"
0!
#195
0"
#198
1"
1!
#201
0"
#204
1"
0!
#207
0"
#210
1"
1!
#213
0"
#216
1"
0!
#219
0"
#222
1"
1!
#225
0"
#228
1"
0!
#231
0"
#234
1"
1!
#237
0"
#240
1"
0!
#243
0"
#246
1"
1!
#249
0"
#252
1"
0!
#255
0"
#258
1"
1!
#261
0"
#264
1"
0!
#267
0"
#270
1"
1!
#273
0"
#276
1"
0!
#279
0"
#282
1"
1!
#285
0"
#288
1"
0!
#291
0"
#294
1"
1!
#297
0"
#300
1"
0!
#303
0"
#306
1"
1!
#309
0"
#312
1"
0!
#315
0"
#318
1"
1!
#321
0"
#324
1"
0!
#327
0"
#330
1"
1!
#333
0"
#336
1"
0!
#339
0"
#342
1"
1!
#345
0"
#348
1"
0!
#351
0"
#354
1"
1!
#357
0"
#360
1"
0!
1#
#363
0"
#366
1"
1!
#369
0"
#372
1"
0!
#375
0"
#378
1"
1!
#381
0"
#384
1"
0!
#387
0"
#390
1"
1!
#393
0"
#396
1"
0!
#399
0"
#402
1"
1!
#405
0"
#408
1"
0!
#411
0"
#414
1"
1!
#417
0"
#420
1"
0!
#423
0"
#426
1"
1!
1$
#429
0"
#432
1"
0!
#435
0"
#438
1"
1!
#441
0"
#444
1"
0!
#447
0"
#450
1"
1!
#453
0"
#456
1"
0!
#459
0"
#462
1"
1!
#465
0"
#468
1"
0!
#471
0"
#474
1"
1!
#477
0"
#480
1"
0!
#483
0"
#486
1"
1!
0$
#489
0"
#492
1"
0!
#495
0"
#498
1"
1!
#501
0"
#504
1"
0!
#507
0"
#510
1"
1!
#513
0"
#516
1"
0!
#519
0"
#522
1"
1!
#525
0"
#528
1"
0!
#531
0"
#534
1"
1!
#537
0"
#540
1"
0!
#543
0"
#546
1"
1!
1$
#549
0"
#552
1"
0!
#555
0"
#558
1"
1!
#561
0"
#564
1"
0!
#567
0"
#570
1"
1!
#573
0"
#576
1"
0!
#579
0"
#582
1"
1!
#585
0"
#588
1"
0!
#591
0"
#594
1"
1!
#597
0"
#600
1"
0!
0#
#603
0"
#606
1"
1!
0$
#609
0"
#612
1"
0!
#615
0"
#618
1"
1!
#621
0"
#624
1"
0!
#627
0"
#630
1"
1!
#633
0"
#636
1"
0!
#639
0"
#642
1"
1!
#645
0"
#648
1"
0!
#651
0"
#654
1"
1!
#657
0"
#660
1"
0!
#663
0"
#666
1"
1!
#669
0"
#672
1"
0!
#675
0"
#678
1"
1!
#681
0"
#684
1"
0!
#687
0"
#690
1"
1!
#693
0"
#696
1"
0!
#699
0"
#702
1"
1!
#705
0"
#708
1"
0!
#711
0"
#714
1"
1!
#717
0"
#720
1"
0!
#723
0"
#726
1"
1!
#729
0"
#732
1"
0!
#735
0"
#738
1"
1!
#741
0"
#744
1"
0!
#747
0"
#750
1"
1!
#753
0"
#756
1"
0!
#759
0"
#762
1"
1!
#765
0"
#768
1"
0!
#771
0"
#774
1"
1!
#777
0"
#780
1"
0!
#783
0"
#786
1"
1!
#789
0"
#792
1"
0!
#795
0"
#798
1"
1!
#801
0"
#804
1"
0!
#807
0"
#810
1"
1!
#813
0"
#816
1"
0!
#819
0"
#822
1"
1!
#825
0"
#828
1"
0!
#831
0"
#834
1"
1!
#837
0"
#840
1"
0!
#843
0"
#846
1"
1!
#849
0"
#852
1"
0!
#855
0"
#858
1"
1!
#861
0"
#864
1"
0!
#867
0"
#870
1"
1!
#873
0"
#876
1"
0!
#879
0"
#882
1"
1!
#885
0"
#888
1"
0!
#891
0"
#894
1"
1!
#897
0"
#900
1"
0!
1#
#903
0"
#906
1"
1!
#909
0"
#912
1"
0!
#915
0"
#918
1"
1!
#921
0"
#924
1"
0!
#927
0"
#930
1"
1!
#933
0"
#936
1"
0!
#939
0"
#942
1"
1!
#945
0"
#948
1"
0!
#951
0"
#954
1"
1!
#957
0"
#960
1"
0!
#963
0"
#966
1"
1!
1$
#969
0"
#972
1"
0!
#975
0"
#978
1"
1!
#981
0"
#984
1"
0!
#987
0"
#990
1"
1!
#993
0"
#996
1"
0!
#999
0"
#1002
1"
1!
#1005
0"
#1008
1"
0!
#1011
0"
#1014
1"
1!
#1017
0"
#1020
1"
0!
#1023
0"
#1026
1"
1!
0$
#1029
0"
#1032
1"
0!
#1035
0"
#1038
1"
1!
#1041
0"
#1044
1"
0!
#1047
0"
#1050
1"
1!
#1053
0"
#1056
1"
0!
#1059
0"
#1062
1"
1!
#1065
0"
#1068
1"
0!
#1071
0"
#1074
1"
1!
#1077
0"
#1080
1"
0!
#1083
0"
#1086
1"
1!
1$
#1089
0"
#1092
1"
0!
#1095
0"
#1098
1"
1!
#1101
0"
#1104
1"
0!
#1107
0"
#1110
1"
1!
#1113
0"
#1116
1"
0!
#1119
0"
#1122
1"
1!
#1125
0"
#1128
1"
0!
#1131
0"
#1134
1"
1!
#1137
0"
#1140
1"
0!
#1143
0"
#1146
1"
1!
0$
#1149
0"
#1152
1"
0!
#1155
0"
#1158
1"
1!
#1161
0"
#1164
1"
0!
#1167
0"
#1170
1"
1!
#1173
0"
#1176
1"
0!
#1179
0"
#1182
1"
1!
#1185
0"
#1188
1"
0!
#1191
0"
#1194
1"
1!
#1197
0"
#1200
1"
0!
#1203
0"
#1206
1"
1!
1$
#1209
0"
#1212
1"
0!
#1215
0"
#1218
1"
1!
#1221
0"
#1224
1"
0!
#1227
0"
#1230
1"
1!
#1233
0"
#1236
1"
0!
#1239
0"
#1242
1"
1!
#1245
0"
#1248
1"
0!
#1251
0"
#1254
1"
1!
#1257
0"
#1260
1"
0!
0#
#1263
0"
#1266
1"
1!
0$
#1269
0"
#1272
1"
0!
#1275
0"
#1278
1"
1!
#1281
0"
#1284
1"
0!
#1287
0"
#1290
1"
1!
#1293
0"
#1296
1"
0!
#1299
0"
#1302
1"
1!
#1305
0"
#1308
1"
0!
#1311
0"
#1314
1"
1!
#1317
0"
#1320
1"
0!
#1323
0"
#1326
1"
1!
#1329
0"
#1332
1"
0!
#1335
0"
#1338
1"
1!
#1341
0"
#1344
1"
0!
#1347
0"
#1350
1"
1!
#1353
0"
#1356
1"
0!
#1359
0"
#1362
1"
1!
#1365
0"
#1368
1"
0!
#1371
0"
#1374
1"
1!
#1377
0"
#1380
1"
0!
#1383
0"
#1386
1"
1!
#1389
0"
#1392
1"
0!
#1395
0"
#1398
1"
1!
#1401
0"
#1404
1"
0!
#1407
0"
#1410
1"
1!
#1413
0"
#1416
1"
0!
#1419
0"
#1422
1"
1!
#1425
0"
#1428
1"
0!
#1431
0"
#1434
1"
1!
#1437
0"
#1440
1"
0!
#1443
0"
#1446
1"
1!
#1449
0"
#1452
1"
0!
#1455
0"
#1458
1"
1!
#1461
0"
#1464
1"
0!
#1467
0"
#1470
1"
1!
#1473
0"
#1476
1"
0!
#1479
0"
#1482
1"
1!
#1485
0"
#1488
1"
0!
#1491
0"
#1494
1"
1!
#1497
0"
#1500
1"
0!
#1503
0"
#1506
1"
1!
#1509
0"
#1512
1"
0!
#1515
0"
#1518
1"
1!
#1521
0"
#1524
1"
0!
#1527
0"
#1530
1"
1!
#1533
0"
#1536
1"
0!
#1539
0"
#1542
1"
1!
#1545
0"
#1548
1"
0!
#1551
0"
#1554
1"
1!
#1557
0"
#1560
1"
0!
#1563
0"
#1566
1"
1!
#1569
0"
#1572
1"
0!
#1575
0"
#1578
1"
1!
#1581
0"
#1584
1"
0!
#1587
0"
#1590
1"
1!
#1593
0"
#1596
1"
0!
#1599
0"
#1602
1"
1!
#1605
0"
#1608
1"
0!
#1611
0"
#1614
1"
1!
#1617
0"
#1620
1"
0!
#1623
0"
#1626
1"
1!
#1629
0"
#1632
1"
0!
#1635
0"
